LICENSE.txt
README.md
pyproject.toml
setup.py
hymd/__init__.py
hymd/__main__.py
hymd/barostat.py
hymd/barostat_scr.py
hymd/compute_angle_forces.f90
hymd/compute_angle_forces__double.f90
hymd/compute_bond_forces.f90
hymd/compute_bond_forces__double.f90
hymd/compute_dihedral_forces.f90
hymd/compute_dihedral_forces__double.f90
hymd/configure_runtime.py
hymd/dipole_reconstruction.f90
hymd/dipole_reconstruction__double.f90
hymd/field.py
hymd/file_io.py
hymd/force.py
hymd/gaussian_core.py
hymd/hamiltonian.py
hymd/input_parser.py
hymd/integrator.py
hymd/logger.py
hymd/main.py
hymd/plumed.py
hymd/pressure.py
hymd/thermostat.py
hymd/version.py
hymd.egg-info/PKG-INFO
hymd.egg-info/SOURCES.txt
hymd.egg-info/dependency_links.txt
hymd.egg-info/requires.txt
hymd.egg-info/top_level.txt
test/test_configure_runtime.py
test/test_distribute_input.py
test/test_field.py
test/test_file_io.py
test/test_force.py
test/test_hamiltonian.py
test/test_input_parser.py
test/test_integrator.py
test/test_logger.py
test/test_plumed.py
test/test_thermostat.py