Metadata-Version: 2.1
Name: hymd
Version: 2.2.0
Summary: Massively parallel hybrid particle-field MD
Home-page: https://github.com/Cascella-Group-UiO/HyMD
Author: Morten Ledum
Author-email: morten.ledum@gmail.com
License: LGPLv3
Classifier: Development Status :: 5 - Production/Stable
Classifier: License :: OSI Approved :: GNU Lesser General Public License v3 (LGPLv3)
Classifier: Intended Audience :: Science/Research
Classifier: Programming Language :: Python
Classifier: Programming Language :: Python :: 3 :: Only
Classifier: Programming Language :: Python :: 3.6
Classifier: Programming Language :: Python :: 3.7
Classifier: Programming Language :: Python :: 3.8
Classifier: Programming Language :: Python :: 3.9
Classifier: Programming Language :: Python :: 3.10
Classifier: Programming Language :: Python :: 3.11
Classifier: Programming Language :: Fortran
Classifier: Topic :: Scientific/Engineering :: Chemistry
Classifier: Topic :: Scientific/Engineering :: Physics
Requires-Python: >=3.6
License-File: LICENSE.txt
Requires-Dist: h5py
Requires-Dist: mpi4py
Requires-Dist: networkx
Requires-Dist: numpy<1.25
Requires-Dist: sympy
Requires-Dist: tomli
Requires-Dist: cython<3
Requires-Dist: mpsort
Requires-Dist: pfft-python
Requires-Dist: pmesh
